{
	"format_version": "1.8.0",
	"animations": {
		"flap": {
			"loop": true,
			"animation_length": 1,
			"bones": {
				"left_wing_anchor": {
					"rotation": {
						"0.0": {
							"vector": [0, 0, 0]
						},
						"0.5": {
							"vector": [0, 0, -45]
						},
						"1.0": {
							"vector": [0, 0, 0]
						}
					}
				},
				"right_wing_anchor": {
					"rotation": {
						"0.0": {
							"vector": [0, 0, 0]
						},
						"0.5": {
							"vector": [0, 0, 45]
						},
						"1.0": {
							"vector": [0, 0, 0]
						}
					}
				}
			}
		},
		"idle": {
			"loop": true,
			"animation_length": 2,
			"bones": {
				"body": {
					"position": {
						"0.0": {
							"vector": [0, 0, 0]
						},
						"1.0": {
							"vector": [0, 2, 0]
						},
						"2.0": {
							"vector": [0, 0, 0]
						}
					}
				}
			}
		}
	},
	"geckolib_format_version": 2
}